bancor3_simulator
