Metadata-Version: 2.1
Name: bancor3-simulator
Version: 1.0.1
Summary: Bancor3 Simulator is an open-source python package developed by the Bancor Research Team. It’s meant to assist designing, testing, and validating Bancor v3 behavior.
Home-page: https://github.com/bancorprotocol/simulator-v3
Author: Bancor Network
Author-email: mike@bancor.network
License: UNKNOWN
Platform: UNKNOWN
Provides-Extra: complete
License-File: LICENSE
